[{"id":"1f0f52e17e88337afd57bf5f62169b77","title":"Chứng khoán Mỹ lập kỷ lục, giá vàng quay đầu tăng","summary":"Cả ba chỉ số chủ chốt của Wall Street cùng lập kỷ lục mới phiên thứ 2 liên tiếp, trong khi giá vàng tăng 40 USD một ounce.","main_image_url":"https:\/\/i1-kinhdoanh.vnecdn.net\/2025\/09\/20\/wall-street-reu-1746235563-174-2255-3049-1758333224.jpg?w=1200&h=0&q=100&dpr=1&fit=crop&s=vWhh80hx6oyHraLhzMEdqg","author_name":"VNExpress","author_id":94,"avatar_url":"public\/img\/avatar\/vnexpress.png","created_at":"2025-09-20 09:27:48","upvotes":0,"comment_count":0,"link":"https:\/\/vnexpress.net\/chung-khoan-my-lap-ky-luc-gia-vang-quay-dau-tang-4941332.html","is_rss":true},{"id":"798d6aefa2e9c12513a4c2cbb4ae1e0c","title":"Doanh nghiệp nào đang muốn lập sàn tiền số?","summary":"Nhiều ngân hàng và công ty chứng khoán ráo riết lập doanh nghiệp thí điểm sàn giao dịch tiền số nhưng phần lớn chưa đáp ứng đủ vốn điều lệ.","main_image_url":"https:\/\/i1-kinhdoanh.vnecdn.net\/2025\/09\/20\/2-1758303205-1758303215.png?w=1200&h=0&q=100&dpr=1&fit=crop&s=8HzsBZn63AlLwnFml7XErw","author_name":"VNExpress","author_id":94,"avatar_url":"public\/img\/avatar\/vnexpress.png","created_at":"2025-09-20 02:18:58","upvotes":0,"comment_count":0,"link":"https:\/\/vnexpress.net\/doanh-nghiep-nao-dang-muon-lap-san-tien-so-4940246.html","is_rss":true},{"id":"3bb38767f48019d317852a56afd74fd7","title":"Thế Giới Di Động thu gần 100.000 tỷ đồng trong 8 tháng","summary":"Tám tháng, doanh thu Thế Giới Di Động tiến sát mốc 100.000 tỷ đồng nhờ các ngành hàng lớn như laptop, điện máy, thực phẩm tươi sống... đều tăng.","main_image_url":"https:\/\/i1-kinhdoanh.vnecdn.net\/2025\/09\/19\/MWG-1758287683-8561-1758287758.jpg?w=1200&h=0&q=100&dpr=1&fit=crop&s=e37nvR_22r7jUM2eB_Ihyw","author_name":"VNExpress","author_id":94,"avatar_url":"public\/img\/avatar\/vnexpress.png","created_at":"2025-09-20 01:48:06","upvotes":0,"comment_count":0,"link":"https:\/\/vnexpress.net\/the-gioi-di-dong-thu-gan-100-000-ty-dong-trong-8-thang-4941284.html","is_rss":true},{"id":"c9c9b2b145c77bafa9e9149da69d4402","title":"Lượng người mua vé Lotto 5\/35 tăng trước kỳ chia giải độc đắc","summary":"Lotto 5\/35 ghi nhận lượng người chơi tăng khi giải độc đắc vượt 12 tỷ đồng và có thể bước vào kỳ chia giải thứ 5 nếu tối nay chưa tìm được chủ nhân.","main_image_url":"https:\/\/i1-kinhdoanh.vnecdn.net\/2025\/09\/20\/v1-1758328646-1758328919-8504-1758328974.png?w=1200&h=0&q=100&dpr=1&fit=crop&s=iAxc2AFsIYcXPDjW1Kpysw","author_name":"VNExpress","author_id":94,"avatar_url":"public\/img\/avatar\/vnexpress.png","created_at":"2025-09-20 09:00:00","upvotes":0,"comment_count":0,"link":"https:\/\/vnexpress.net\/luong-nguoi-mua-ve-lotto-5-35-tang-truoc-ky-chia-giai-doc-dac-4941210.html","is_rss":true},{"id":"d7b1266cce01e9a6c1d51a8382b00144","title":"Nhà đầu tư ngoại nắm trái phiếu chính phủ Mỹ nhiều kỷ lục","summary":"Bộ Tài chính Mỹ cho biết giá trị số trái phiếu chính phủ nước này trong tay nhà đầu tư ngoại đã lên kỷ lục 9.159 tỷ USD trong tháng 7.","main_image_url":"https:\/\/i1-kinhdoanh.vnecdn.net\/2025\/09\/19\/usd-lebanon-1758274551-1758274-8997-5436-1758274684.jpg?w=1200&h=0&q=100&dpr=1&fit=crop&s=5DGDLnt0hHqcU74Ye16PFQ","author_name":"VNExpress","author_id":94,"avatar_url":"public\/img\/avatar\/vnexpress.png","created_at":"2025-09-19 23:27:58","upvotes":0,"comment_count":0,"link":"https:\/\/vnexpress.net\/nha-dau-tu-ngoai-nam-trai-phieu-chinh-phu-my-nhieu-ky-luc-4941162.html","is_rss":true},{"id":"99ca89ff618d3c28f16ced76cac18de3","title":"Cơ hội phục hồi Intel khi được Nvidia đầu tư","summary":"Nvidia đầu tư 5 tỷ USD sẽ giúp củng cố tình hình tài chính Intel, tăng khả năng cạnh tranh sản phẩm vi xử lý nhưng mảng dịch vụ gia công vẫn chưa lối thoát.","main_image_url":"https:\/\/i1-kinhdoanh.vnecdn.net\/2025\/09\/19\/intel-computex-2024-vnexpress-1111-9889-1758272114.jpg?w=1200&h=0&q=100&dpr=1&fit=crop&s=jxA9KlbVPRb_7x_9gO2sOA","author_name":"VNExpress","author_id":94,"avatar_url":"public\/img\/avatar\/vnexpress.png","created_at":"2025-09-19 16:33:08","upvotes":0,"comment_count":0,"link":"https:\/\/vnexpress.net\/co-hoi-phuc-hoi-intel-khi-duoc-nvidia-dau-tu-4941143.html","is_rss":true},{"id":"726e681c85fe8490adb65714686c004b","title":"Chứng khoán giảm 4 phiên liên tiếp","summary":"Chứng khoán kết tuần sụt gần 7 điểm và đã giảm 4 phiên liên tiếp nhưng thanh khoản ở mức thấp dù được cổ phiếu Vingroup nâng đỡ.","main_image_url":"https:\/\/i1-kinhdoanh.vnecdn.net\/2025\/09\/19\/quyn8466-1758270333-2138-1758271083.jpg?w=1200&h=0&q=100&dpr=1&fit=crop&s=W7LrQWM7f3CcWrf8TERm6g","author_name":"VNExpress","author_id":94,"avatar_url":"public\/img\/avatar\/vnexpress.png","created_at":"2025-09-19 16:17:59","upvotes":0,"comment_count":0,"link":"https:\/\/vnexpress.net\/chung-khoan-hom-nay-19-9-vn-index-giam-4-phien-lien-tiep-4941194.html","is_rss":true},{"id":"cc9e59f60483a862b547091e253d83cc","title":"Giá xoài cát Hòa Lộc tăng mạnh","summary":"Giá xoài cát Hòa Lộc tại An Giang tăng gấp rưỡi so với những tháng đầu năm do nguồn cung giảm trong lúc nhu cầu tiêu thụ cao.","main_image_url":"https:\/\/i1-kinhdoanh.vnecdn.net\/2025\/09\/17\/xoai-1758077562-1758077637-4367-1758077913.jpg?w=1200&h=0&q=100&dpr=1&fit=crop&s=RRA3A23RFGPnyU_mXlloTw","author_name":"VNExpress","author_id":94,"avatar_url":"public\/img\/avatar\/vnexpress.png","created_at":"2025-09-19 12:35:15","upvotes":0,"comment_count":0,"link":"https:\/\/vnexpress.net\/gia-xoai-cat-hoa-loc-tang-manh-4940052.html","is_rss":true},{"id":"a51e98c745d722f84378901540c4f986","title":"Fed mở đường cho các nước châu Á giảm lãi suất","summary":"Ngân hàng trung ương các nước châu Á có dư địa nới lỏng chính sách lớn hơn, sau khi Cục Dự trữ liên bang (Mỹ) giảm lãi suất tuần này.","main_image_url":"https:\/\/i1-kinhdoanh.vnecdn.net\/2025\/09\/19\/seoul-1758254813-1758254868-2369-1758255000.jpg?w=1200&h=0&q=100&dpr=1&fit=crop&s=_oqaHfC-epHevH1zPGVPLw","author_name":"VNExpress","author_id":94,"avatar_url":"public\/img\/avatar\/vnexpress.png","created_at":"2025-09-19 11:31:00","upvotes":0,"comment_count":0,"link":"https:\/\/vnexpress.net\/fed-mo-duong-cho-cac-nuoc-chau-a-giam-lai-suat-4940967.html","is_rss":true},{"id":"63b22797326fad8ce0189489e8f932ca","title":"Công ty cà phê trả cổ tức 48.000 đồng một cổ phiếu","summary":"Vinacafé Biên Hòa - công ty con chuyên bán cà phê của Tập đoàn Masan - chốt ngày trả cổ tức bằng tiền với mức 48.000 đồng cho mỗi cổ phiếu.","main_image_url":"https:\/\/i1-kinhdoanh.vnecdn.net\/2025\/09\/19\/20200622-102537-01-jpeg-175825-4407-9787-1758251673.jpg?w=1200&h=0&q=100&dpr=1&fit=crop&s=SMQm4FEFWrGaXuurwPxKgw","author_name":"VNExpress","author_id":94,"avatar_url":"public\/img\/avatar\/vnexpress.png","created_at":"2025-09-19 10:37:36","upvotes":0,"comment_count":0,"link":"https:\/\/vnexpress.net\/cong-ty-ca-phe-tra-co-tuc-48-000-dong-mot-co-phieu-4940993.html","is_rss":true},{"id":"a7e3aa84d3d2eff772cc431d1b76a1a3","title":"ExxonMobil dừng dự án tái chế 80.000 tấn rác nhựa","summary":"ExxonMobil, tập đoàn dầu khí Mỹ, tạm dừng đầu tư hai dự án tái chế nhựa tại Hà Lan và Bỉ, bởi dự thảo \"phân biệt đối xử\" với phương pháp tái chế hóa học của EU.","main_image_url":"https:\/\/i1-kinhdoanh.vnecdn.net\/2025\/09\/19\/blavgebj3rintepmrvx3vvf3ji-175-4034-9254-1758248402.png?w=1200&h=0&q=100&dpr=1&fit=crop&s=OO4lphMDuYMEZkEd4kUiqg","author_name":"VNExpress","author_id":94,"avatar_url":"public\/img\/avatar\/vnexpress.png","created_at":"2025-09-19 10:31:46","upvotes":0,"comment_count":0,"link":"https:\/\/vnexpress.net\/exxonmobil-dung-du-an-tai-che-80-000-tan-rac-nhua-4940959.html","is_rss":true},{"id":"6ae7ebae018aada0e3437ace6b326a82","title":"Mức thuế thu nhập 35% của Việt Nam thuộc nhóm cao trong khu vực","summary":"Theo Deloitte Việt Nam, mức thuế tối đa 35% trong biểu thuế của Việt Nam ngang với Thái Lan và Philippines, trong khi Singapore chỉ áp mức cao nhất 24%, Malaysia và Myanmar là 30%.","main_image_url":"https:\/\/i1-kinhdoanh.vnecdn.net\/2025\/09\/17\/huy6982-1757915753-1757915779-4894-1758101905.jpg?w=1200&h=0&q=100&dpr=1&fit=crop&s=M78ERFr21hgFsFbOA7rQJw","author_name":"VNExpress","author_id":94,"avatar_url":"public\/img\/avatar\/vnexpress.png","created_at":"2025-09-19 06:30:00","upvotes":0,"comment_count":0,"link":"https:\/\/vnexpress.net\/muc-thue-thu-nhap-35-cua-viet-nam-thuoc-nhom-cao-trong-khu-vuc-4939244.html","is_rss":true}]